{
	"credit": "Hi",
	"parent": "block/block",
	"ambientocclusion": false,
	"textures": {
		"bottom": "block/cactus_bottom",
		"top": "block/cactus_top",
		"particle": "block/cactus_side",
		"side": "block/cactus_side"
	},
	"elements": [
		{
			"name": "Block",
			"from": [1, 0, 1],
			"to": [15, 16, 15],
			"rotation": {"angle": 0, "axis": "y", "origin": [9, 8, 9]},
			"faces": {
				"north": {"uv": [14, 0, 0, 16], "texture": "#side"},
				"east": {"uv": [14, 0, 0, 16], "texture": "#side"},
				"south": {"uv": [0, 0, 14, 16], "texture": "#side"},
				"west": {"uv": [0, 0, 14, 16], "texture": "#side"},
				"up": {"uv": [0, 0, 14, 14], "texture": "#top"},
				"down": {"uv": [0, 0, 14, 14], "texture": "#bottom"}
			}
		},
		{
			"name": "Spike",
			"from": [-0.5, 4, 0.5],
			"to": [1.5, 6, 0.5],
			"rotation": {"angle": -45, "axis": "y", "origin": [0.5, 5, 0.5]},
			"faces": {
				"north": {"uv": [0, 10, 2, 12], "texture": "#side"},
				"east": {"uv": [0, 10, 2, 12], "texture": "#side"},
				"south": {"uv": [0, 10, 2, 12], "texture": "#side"},
				"west": {"uv": [0, 10, 2, 12], "texture": "#side"},
				"up": {"uv": [0, 10, 2, 12], "texture": "#side"},
				"down": {"uv": [0, 10, 2, 12], "texture": "#side"}
			}
		},
		{
			"name": "Spike",
			"from": [-1, 4, 15],
			"to": [1, 6, 15],
			"rotation": {"angle": 0, "axis": "y", "origin": [0, 5, 15]},
			"faces": {
				"north": {"uv": [0, 10, 2, 12], "texture": "#side"},
				"east": {"uv": [0, 10, 2, 12], "texture": "#side"},
				"south": {"uv": [0, 10, 2, 12], "texture": "#side"},
				"west": {"uv": [0, 10, 2, 12], "texture": "#side"},
				"up": {"uv": [0, 10, 2, 12], "texture": "#side"},
				"down": {"uv": [0, 10, 2, 12], "texture": "#side"}
			}
		},
		{
			"name": "Spike",
			"from": [15, 10, 1],
			"to": [17, 12, 1],
			"rotation": {"angle": 0, "axis": "y", "origin": [16, 11, 1]},
			"faces": {
				"north": {"uv": [0, 10, 2, 12], "texture": "#side"},
				"east": {"uv": [0, 10, 2, 12], "texture": "#side"},
				"south": {"uv": [0, 10, 2, 12], "texture": "#side"},
				"west": {"uv": [0, 10, 2, 12], "texture": "#side"},
				"up": {"uv": [0, 10, 2, 12], "texture": "#side"},
				"down": {"uv": [0, 10, 2, 12], "texture": "#side"}
			}
		},
		{
			"name": "Spike",
			"from": [1, 10, 15],
			"to": [1, 12, 17],
			"rotation": {"angle": 0, "axis": "y", "origin": [1, 11, 16]},
			"faces": {
				"north": {"uv": [0, 10, 2, 12], "texture": "#side"},
				"east": {"uv": [0, 10, 2, 12], "texture": "#side"},
				"south": {"uv": [0, 10, 2, 12], "texture": "#side"},
				"west": {"uv": [0, 10, 2, 12], "texture": "#side"},
				"up": {"uv": [0, 10, 2, 12], "rotation": 270, "texture": "#side"},
				"down": {"uv": [0, 10, 2, 12], "rotation": 90, "texture": "#side"}
			}
		},
		{
			"name": "Spike",
			"from": [15, 4, -1],
			"to": [15, 6, 1],
			"rotation": {"angle": 0, "axis": "y", "origin": [15, 5, 0]},
			"faces": {
				"north": {"uv": [0, 10, 2, 12], "texture": "#side"},
				"east": {"uv": [0, 10, 2, 12], "texture": "#side"},
				"south": {"uv": [0, 10, 2, 12], "texture": "#side"},
				"west": {"uv": [0, 10, 2, 12], "texture": "#side"},
				"up": {"uv": [0, 10, 2, 12], "rotation": 270, "texture": "#side"},
				"down": {"uv": [0, 10, 2, 12], "rotation": 90, "texture": "#side"}
			}
		},
		{
			"name": "Spike",
			"from": [14.5, 10, 15.5],
			"to": [16.5, 12, 15.5],
			"rotation": {"angle": -45, "axis": "y", "origin": [15.5, 11, 15.5]},
			"faces": {
				"north": {"uv": [0, 10, 2, 12], "texture": "#side"},
				"east": {"uv": [0, 10, 2, 12], "texture": "#side"},
				"south": {"uv": [0, 10, 2, 12], "texture": "#side"},
				"west": {"uv": [0, 10, 2, 12], "texture": "#side"},
				"up": {"uv": [0, 10, 2, 12], "texture": "#side"},
				"down": {"uv": [0, 10, 2, 12], "texture": "#side"}
			}
		},
		{
			"name": "Spike",
			"from": [8, 12, 15],
			"to": [8, 14, 17],
			"rotation": {"angle": 0, "axis": "y", "origin": [8, 13, 16]},
			"faces": {
				"north": {"uv": [0, 10, 2, 12], "texture": "#side"},
				"east": {"uv": [0, 10, 2, 12], "texture": "#side"},
				"south": {"uv": [0, 10, 2, 12], "texture": "#side"},
				"west": {"uv": [0, 10, 2, 12], "texture": "#side"},
				"up": {"uv": [0, 10, 2, 12], "rotation": 90, "texture": "#side"},
				"down": {"uv": [0, 10, 2, 12], "rotation": 270, "texture": "#side"}
			}
		},
		{
			"name": "Spike",
			"from": [8, 12, -1],
			"to": [8, 14, 1],
			"rotation": {"angle": 0, "axis": "y", "origin": [8, 13, 0]},
			"faces": {
				"north": {"uv": [0, 10, 2, 12], "texture": "#side"},
				"east": {"uv": [0, 10, 2, 12], "texture": "#side"},
				"south": {"uv": [0, 10, 2, 12], "texture": "#side"},
				"west": {"uv": [0, 10, 2, 12], "texture": "#side"},
				"up": {"uv": [0, 10, 2, 12], "rotation": 90, "texture": "#side"},
				"down": {"uv": [0, 10, 2, 12], "rotation": 270, "texture": "#side"}
			}
		},
		{
			"name": "Spike",
			"from": [15, 12, 8],
			"to": [17, 14, 8],
			"rotation": {"angle": 0, "axis": "y", "origin": [16, 13, 8]},
			"faces": {
				"north": {"uv": [0, 10, 2, 12], "texture": "#side"},
				"east": {"uv": [0, 10, 2, 12], "texture": "#side"},
				"south": {"uv": [0, 10, 2, 12], "texture": "#side"},
				"west": {"uv": [0, 10, 2, 12], "texture": "#side"},
				"up": {"uv": [0, 10, 2, 12], "texture": "#side"},
				"down": {"uv": [0, 10, 2, 12], "texture": "#side"}
			}
		},
		{
			"name": "Spike",
			"from": [-1, 12, 8],
			"to": [1, 14, 8],
			"rotation": {"angle": 0, "axis": "y", "origin": [0, 13, 8]},
			"faces": {
				"north": {"uv": [0, 10, 2, 12], "texture": "#side"},
				"east": {"uv": [0, 10, 2, 12], "texture": "#side"},
				"south": {"uv": [0, 10, 2, 12], "texture": "#side"},
				"west": {"uv": [0, 10, 2, 12], "texture": "#side"},
				"up": {"uv": [0, 10, 2, 12], "texture": "#side"},
				"down": {"uv": [0, 10, 2, 12], "texture": "#side"}
			}
		}
	]
}